sequence_detector.v
// 1011 Sequence Detector - Moore FSM
module sequence_detector (
    input clk,            
    input reset,          // Resets when 0
    input data_in,        // input bit 1 or 0
    output reg detected_moore,   // high (1) when sequence 1011 is found
    output wire detected_mealy
    // reg because it will store the value
);

    parameter S_IDLE  = 3'b000, // Initial state (the area that circuit is waiting)
              S_1     = 3'b001, // Sequence 1 
              S_10    = 3'b010, // 10 
              S_101   = 3'b011, // 101
              S_1011  = 3'b100; // 1011

    reg [2:0] current_state, next_state; //3 bit


    always @(posedge clk or negedge reset) begin //sequential logic with clk 
    //Using a non-blocking block allows multiple printers to process jobs simultaneously.
        if (!reset) // if reset result is !0 result is true (reverse logic)
            current_state <= S_IDLE;
        else
            current_state <= next_state;
    end
 
    // Decides where to go based on the current state and input bit
    always @(*) begin //combinational logic
        case (current_state)
            S_IDLE:  next_state = (data_in) ? S_1    : S_IDLE; // if state is 1 go to S_1
            //if state is 0 stay in idle
            S_1:     next_state = (data_in) ? S_1    : S_10;
            S_10:    next_state = (data_in) ? S_101  : S_IDLE;
            S_101:   next_state = (data_in) ? S_1011 : S_10;
            S_1011:  next_state = (data_in) ? S_1    : S_10; // Overlap support
            default: next_state = S_IDLE;
        endcase
    end

    // In Moore, output only depends on the current state
//Moore output
always @(*) begin
    detected_moore = (current_state == S_1011) ? 1 : 0;
end
// BLOK 4 - Mealy çıkışı
assign detected_mealy = (current_state == S_101 && data_in == 1) ? 1'b1 : 1'b0;

endmodule

tb_sequence_detector.v
`timescale 1ns / 1ps

module tb_sequence_detector();

    // Test signals
    reg clk;
    reg reset;
    reg data_in;
    wire detected_moore, detected_mealy;

    // Instantiate the design (Connect the test signals to the module)
    sequence_detector dut (
        .clk(clk),
        .reset(reset),
        .data_in(data_in),
        .detected_moore(detected_moore),
        .detected_mealy(detected_mealy)
    );

    // Clock generation: 10ns period (100MHz)
    always #5 clk = ~clk;

    initial begin
        // Initialize signals
        clk = 0;
        reset = 0;      // Start with reset active
        data_in = 0;

        #15 reset = 1;  // Deactivate reset after 15ns

        // Sending test sequence: 1 -> 0 -> 1 -> 1
        #10 data_in = 1;
        #10 data_in = 0;
        #10 data_in = 1;
        #10 data_in = 1; // Sequence complete
        #10 $display("Moore: %b  Mealy: %b (ikisi de 1 olmali)", detected_moore, detected_mealy);

        // Add some random bits and repeat
        #10 data_in = 0;
        #10 data_in = 1;
        #10 data_in = 0;
        #10 data_in = 1;
        #10 data_in = 1; // Second sequence complete
        #10 $display("Moore: %b  Mealy: %b", detected_moore, detected_mealy);

        #20 $finish;
    end


    // Create waveform file for GTKWave
    initial begin
        $dumpfile("test_results.vcd");
        $dumpvars(0, tb_sequence_detector);
    end

endmodule

test_results.vcd
$date
	Thu Apr 30 12:51:47 2026
$end
$version
	Icarus Verilog
$end
$timescale
	1ps
$end
$scope module tb_sequence_detector $end
$var wire 1 ! detected_moore $end
$var wire 1 " detected_mealy $end
$var reg 1 # clk $end
$var reg 1 $ data_in $end
$var reg 1 % reset $end
$scope module dut $end
$var wire 1 # clk $end
$var wire 1 $ data_in $end
$var wire 1 % reset $end
$var wire 1 " detected_mealy $end
$var parameter 3 & S_1 $end
$var parameter 3 ' S_10 $end
$var parameter 3 ( S_101 $end
$var parameter 3 ) S_1011 $end
$var parameter 3 * S_IDLE $end
$var reg 3 + current_state [2:0] $end
$var reg 1 ! detected_moore $end
$var reg 3 , next_state [2:0] $end
$upscope $end
$upscope $end
$enddefinitions $end
$comment Show the parameter values. $end
$dumpall
b0 *
b100 )
b11 (
b10 '
b1 &
$end
#0
$dumpvars
b0 ,
b0 +
0%
0$
0#
0"
0!
$end
#5000
1#
#10000
0#
#15000
1#
1%
#20000
0#
#25000
b1 +
b1 ,
1#
1$
#30000
0#
#35000
b10 +
b0 ,
1#
0$
#40000
0#
#45000
1"
b11 +
b100 ,
1#
1$
#50000
0#
#55000
0"
1!
b1 ,
b100 +
1#
#60000
0#
#65000
0!
b1 +
1#
#70000
0#
#75000
b10 +
b0 ,
1#
0$
#80000
0#
#85000
1"
b11 +
b100 ,
1#
1$
#90000
0#
#95000
b10 +
0"
b0 ,
1#
0$
#100000
0#
#105000
1"
b11 +
b100 ,
1#
1$
#110000
0#
#115000
0"
1!
b1 ,
b100 +
1#
#120000
0#
#125000
0!
b1 +
1#
